tmticket/__init__.py
tmticket/client.py
tmticket/model.py
tmticket/query.py
tmticket-0.2.18.dist-info/METADATA
tmticket-0.2.18.dist-info/WHEEL
tmticket-0.2.18.dist-info/top_level.txt
tmticket-0.2.18.dist-info/RECORD
